jsonrpc_netstrings
