Metadata-Version: 1.0
Name: JsonRpc-Netstrings
Version: 0.2-dev
Summary: Lightweight json-rpc library for building TCP (Netstring) clients -- see txJsonRpc-Netstrings for building servers.
Home-page: http://github.com/teltech/JsonRpc-Netstrings
Author: TelTech Systems
Author-email: UNKNOWN
License: UNKNOWN
Platform: UNKNOWN
